grompt/__init__.py
grompt/utils.py
grompt/application/__init__.py
grompt/application/cli/__init__.py
grompt/application/cli/main.py
grompt/application/cli/commands/__init__.py
grompt/application/cli/commands/add.py
grompt/application/cli/commands/commit.py
grompt/application/cli/commands/init.py
grompt/core/__init__.py
grompt/core/execution.py
grompt/core/prompt.py
grompt/core/template.py
grompt/core/validator.py
grompt/infrastructure/__init__.py
grompt/infrastructure/storage/__init__.py
grompt/infrastructure/storage/hasher.py
grompt/infrastructure/storage/yaml_loader.py
grompt-0.3.1.dist-info/licenses/LICENSE
grompt-0.3.1.dist-info/METADATA
grompt-0.3.1.dist-info/WHEEL
grompt-0.3.1.dist-info/entry_points.txt
grompt-0.3.1.dist-info/top_level.txt
grompt-0.3.1.dist-info/RECORD
