Metadata-Version: 2.4
Name: grompt
Version: 0.3.1
Summary: Git for prompts - Manage LLM prompts with version control
Author-email: Michael Karotsieris <mkarots@users.noreply.github.com>
License: MIT
Project-URL: Homepage, https://github.com/mkarots/grompt
Project-URL: Documentation, https://github.com/mkarots/grompt#readme
Project-URL: Repository, https://github.com/mkarots/grompt
Project-URL: Issues, https://github.com/mkarots/grompt/issues
Keywords: llm,prompts,version-control,ai,gpt
Classifier: Development Status :: 3 - Alpha
Classifier: Intended Audience :: Developers
Classifier: License :: OSI Approved :: MIT License
Classifier: Programming Language :: Python :: 3
Classifier: Programming Language :: Python :: 3.9
Classifier: Programming Language :: Python :: 3.10
Classifier: Programming Language :: Python :: 3.11
Classifier: Programming Language :: Python :: 3.12
Requires-Python: >=3.9
License-File: LICENSE
Requires-Dist: pyyaml>=6.0
Requires-Dist: jinja2>=3.1.0
Requires-Dist: click>=8.1.0
Provides-Extra: dev
Requires-Dist: pytest>=7.0.0; extra == "dev"
Requires-Dist: pytest-cov>=4.0.0; extra == "dev"
Requires-Dist: black>=23.0.0; extra == "dev"
Requires-Dist: ruff>=0.1.0; extra == "dev"
Requires-Dist: mypy>=1.0.0; extra == "dev"
Requires-Dist: types-PyYAML>=6.0.0; extra == "dev"
Provides-Extra: tokenizer
Requires-Dist: tiktoken>=0.5.0; extra == "tokenizer"
Dynamic: license-file
